asyncwatch-0.1.dist-info/RECORD
asyncwatch-0.1.dist-info/WHEEL
asyncwatch-0.1.dist-info/METADATA
asyncwatch-0.1.dist-info/top_level.txt
asyncwatch-0.1.dist-info/metadata.json
asyncwatch-0.1.dist-info/DESCRIPTION.rst
asyncwatch/inotify.cpython-35m-x86_64-linux-gnu.so
asyncwatch/constants.py
asyncwatch/ffibuilder.py
asyncwatch/__init__.py
asyncwatch/monitor.py
asyncwatch/tests/__init__.py
asyncwatch/tests/test_monitor.py
