Metadata-Version: 2.0
Name: asyncwatch
Version: 0.1
Summary: An asyncronous inotify wrapper based on curio
Home-page: UNKNOWN
Author: Zahari Kassabov
Author-email: UNKNOWN
License: MIT
Platform: UNKNOWN
Classifier: Development Status :: 3 - Alpha
Classifier: Intended Audience :: Developers
Classifier: License :: OSI Approved :: MIT License
Classifier: Programming Language :: Python :: 3.5
Requires-Dist: cffi (>=1.0)
Requires-Dist: curio
